Metadata-Version: 1.0
Name: super-distributions
Version: 0.1.1
Summary: Gaussian and Binomial distributions
Home-page: UNKNOWN
Author: Narayan Sharma
Author-email: narayansharma275@gmail.com
License: UNKNOWN
Platform: UNKNOWN
